{
  "video_id": "2pjhe6-QyLg",
  "title": "The Difference Between Material and Spiritual Activity | Sri Suvyakta Narasimha Dasa",
  "speaker": "HG Suvyakta Narasimha Dasa",
  "youtube_url": "https://www.youtube.com/watch?v=2pjhe6-QyLg",
  "segments": [
    {
      "start_time": 0,
      "end_time": 26,
      "verse_references": [],
      "themes": [
        "material fatigue",
        "work-life balance"
      ],
      "content_type": "analogy",
      "circle_fit": [
        4
      ],
      "key_quote": "Otherwise, he'll get burnt out.",
      "summary": "The speaker uses the example of the need for breaks and vacations in material work to illustrate the difference with spiritual activity.",
      "timestamp_url": "https://youtu.be/2pjhe6-QyLg?t=0"
    },
    {
      "start_time": 27,
      "end_time": 56,
      "verse_references": [],
      "themes": [
        "devotional service",
        "spiritual satisfaction",
        "transcendental nature"
      ],
      "content_type": "philosophy",
      "circle_fit": [
        1,
        2
      ],
      "key_quote": "Even 24 hours in a day is not enough. I want more time. I want to do more.",
      "summary": "The speaker explains that devotional service to Krishna is never tiring because it is transcendental and provides constant satisfaction.",
      "timestamp_url": "https://youtu.be/2pjhe6-QyLg?t=27"
    }
  ]
}