{
  "video_id": "8E1xQmrJR0M",
  "title": "Doubtless Understanding of Krishna | HG Chanchalapathi Dasa | SB 5 .1.4 | 21.06.2024",
  "speaker": "HG Chanchalapathi Dasa",
  "youtube_url": "https://www.youtube.com/watch?v=8E1xQmrJR0M",
  "segments": [
    {
      "start_time": 60,
      "end_time": 144,
      "verse_references": [],
      "themes": [
        "Krishna consciousness",
        "Grihavrata",
        "Doubt"
      ],
      "content_type": "philosophy",
      "circle_fit": [
        1,
        2
      ],
      "key_quote": "A Grihavrata, one who has taken a vow to execute family duties, has no chance to become Krishna conscious.",
      "summary": "King Pariksit expresses his doubt about how someone attached to family can become Krishna conscious, referencing Prahlada Maharaj's statement about Grihavratas.",
      "timestamp_url": "https://youtu.be/8E1xQmrJR0M?t=60"
    },
    {
      "start_time": 147,
      "end_time": 326,
      "verse_references": [],
      "themes": [
        "Priyavrata",
        "Attachment",
        "Perfection",
        "Krishna Consciousness"
      ],
      "content_type": "philosophy",
      "circle_fit": [
        1,
        2
      ],
      "key_quote": "This is very surprising that he became Krishne Mathihi. He became attached to Krishna. Became Krishna conscious.",
      "summary": "The speaker explains King Pariksit's question about how Priyavrata, despite being attached to family, achieved perfection in Krishna consciousness (Krishne Mathihi).",
      "timestamp_url": "https://youtu.be/8E1xQmrJR0M?t=147"
    },
    {
      "start_time": 333,
      "end_time": 505,
      "verse_references": [],
      "themes": [
        "Perfection",
        "Quest for Perfection",
        "Spiritual Knowledge"
      ],
      "content_type": "philosophy",
      "circle_fit": [
        2,
        3
      ],
      "key_quote": "There should be a search for perfection in human life...Should be the dominant aspect of human life.",
      "summary": "The speaker emphasizes the importance of the quest for perfection in human life, noting that without spiritual knowledge, people often misinterpret what true perfection is.",
      "timestamp_url": "https://youtu.be/8E1xQmrJR0M?t=333"
    },
    {
      "start_time": 510,
      "end_time": 673,
      "verse_references": [],
      "themes": [
        "Material Achievements",
        "Power",
        "Fame",
        "Transience"
      ],
      "content_type": "analogy",
      "circle_fit": [
        2,
        4
      ],
      "key_quote": "But then, where is he now? Where is that person?",
      "summary": "The speaker illustrates the transience of material achievements like power and fame by referencing historical figures like Mahatma Gandhi and Napoleon, questioning their current relevance.",
      "timestamp_url": "https://youtu.be/8E1xQmrJR0M?t=510"
    },
    {
      "start_time": 676,
      "end_time": 822,
      "verse_references": [],
      "themes": [
        "Attraction",
        "Opulence",
        "Krishna",
        "All-Attractive"
      ],
      "content_type": "philosophy",
      "circle_fit": [
        2,
        3
      ],
      "key_quote": "Krishna has all these opulences to an unlimited extent. And hence, He becomes captivating.",
      "summary": "The speaker explains that we are naturally attracted to power, influence, and fame, and that Krishna, possessing all these qualities to an unlimited extent, is the ultimate object of attraction.",
      "timestamp_url": "https://youtu.be/8E1xQmrJR0M?t=676"
    },
    {
      "start_time": 837,
      "end_time": 913,
      "verse_references": [],
      "themes": [
        "Krishna",
        "Opulence",
        "Perfection",
        "Krishna Consciousness"
      ],
      "content_type": "philosophy",
      "circle_fit": [
        1,
        2
      ],
      "key_quote": "When your consciousness is attached to Krishna, that is Siddhi. That is the infallible perfection.",
      "summary": "The speaker reiterates that Krishna is all-attractive and that achieving perfection (Siddhi) means having one's consciousness attached to Krishna.",
      "timestamp_url": "https://youtu.be/8E1xQmrJR0M?t=837"
    },
    {
      "start_time": 917,
      "end_time": 1026,
      "verse_references": [],
      "themes": [
        "Krishna Consciousness",
        "Grahavrata",
        "Consciousness",
        "Development"
      ],
      "content_type": "philosophy",
      "circle_fit": [
        1,
        2
      ],
      "key_quote": "If our consciousness becomes absorbed, consciousness becomes attached, to Krishna, that is considered to be Siddhirabhut.",
      "summary": "The speaker references Prahlada Maharaj's words and emphasizes that Krishna consciousness is a development in our consciousness, and perfection is achieved when our consciousness is attached to Krishna.",
      "timestamp_url": "https://youtu.be/8E1xQmrJR0M?t=917"
    },
    {
      "start_time": 1027,
      "end_time": 1198,
      "verse_references": [],
      "themes": [
        "Absolute Truth",
        "Devotion",
        "Father and Mother",
        "Krishna"
      ],
      "content_type": "philosophy",
      "circle_fit": [
        1,
        2
      ],
      "key_quote": "Just like we have to be devoted, to our partial cause, Father and mother, we should also be, Absolutely devoted, To our absolute cause, Krishna.",
      "summary": "The speaker draws an analogy between devotion to parents (partial cause) and devotion to Krishna (absolute cause), arguing that we should be absolutely devoted to Krishna as our ultimate source.",
      "timestamp_url": "https://youtu.be/8E1xQmrJR0M?t=1027"
    },
    {
      "start_time": 1202,
      "end_time": 1273,
      "verse_references": [],
      "themes": [
        "Enlightenment",
        "Ultimate Cause",
        "Krishna Consciousness",
        "Rupa Goswami"
      ],
      "content_type": "philosophy",
      "circle_fit": [
        1,
        2
      ],
      "key_quote": "Becoming Krishnamatihi, Who is Krishna, Who we are, And becoming attached to Krishna...Is considered to be the highest, Perfection.",
      "summary": "The speaker explains that devotion to Krishna is a function of enlightenment and that becoming absorbed in Krishna is the highest perfection, mentioning Srila Prabhupada's coining of the term 'Krishna consciousness' based on Rupa Goswami's expression.",
      "timestamp_url": "https://youtu.be/8E1xQmrJR0M?t=1202"
    },
    {
      "start_time": 1273,
      "end_time": 1357,
      "verse_references": [],
      "themes": [
        "Krishna Bhakti Rasa",
        "Matihi",
        "Consciousness",
        "Perfection"
      ],
      "content_type": "philosophy",
      "circle_fit": [
        1,
        2
      ],
      "key_quote": "Krishna bhakti is not a dry, Concept, No, it is full of, Rasa, It's full of juice, Krishna bhakti rasa, Bhavitha, Imbued, Absorbed, Immersed in, Matihi.",
      "summary": "The speaker elaborates on the concept of 'Krishna bhakti rasa bhavitha matihi,' emphasizing that Krishna bhakti is full of mellow and juice, and that being absorbed in it is the perfection of life.",
      "timestamp_url": "https://youtu.be/8E1xQmrJR0M?t=1273"
    },
    {
      "start_time": 1357,
      "end_time": 1458,
      "verse_references": [],
      "themes": [
        "Shukadeva Goswami",
        "Hare Guna",
        "Captivation",
        "Consciousness"
      ],
      "content_type": "philosophy",
      "circle_fit": [
        1,
        2
      ],
      "key_quote": "Shukadeva Goswami's consciousness was, He was, Captivated, Charmed, By, Hare guna.",
      "summary": "The speaker describes Shukadeva Goswami's consciousness as being captivated by the qualities of Lord Hari (Krishna), contrasting it with the materialistic person's attraction to trivial things.",
      "timestamp_url": "https://youtu.be/8E1xQmrJR0M?t=1357"
    },
    {
      "start_time": 1458,
      "end_time": 1564,
      "verse_references": [],
      "themes": [
        "Guru",
        "Krishna Consciousness",
        "Materialism",
        "Development"
      ],
      "content_type": "philosophy",
      "circle_fit": [
        1,
        2
      ],
      "key_quote": "At least to our, In our situation, We have at least boarded the, Train, Which is, Heading in the right, Which will head in the right direction.",
      "summary": "The speaker shares an anecdote about Prabhupada and emphasizes that devotees have at least boarded the 'train' of Krishna consciousness, heading in the right direction, and that one can develop that consciousness.",
      "timestamp_url": "https://youtu.be/8E1xQmrJR0M?t=1458"
    },
    {
      "start_time": 1564,
      "end_time": 1655,
      "verse_references": [],
      "themes": [
        "Krishnamatihi",
        "Krishna Consciousness",
        "Perfection",
        "Society"
      ],
      "content_type": "philosophy",
      "circle_fit": [
        1,
        2
      ],
      "key_quote": "Look at the good fortune we all have. We have become part of that society which is going to teach us a certain consciousness which is described in the Vedic literature as the highest perfection.",
      "summary": "The speaker reiterates that Krishnamatihi (Krishna consciousness) is perfection and expresses gratitude for being part of a society that teaches this consciousness, which is described in Vedic literature.",
      "timestamp_url": "https://youtu.be/8E1xQmrJR0M?t=1564"
    },
    {
      "start_time": 1655,
      "end_time": 1771,
      "verse_references": [
        "BG 15.19"
      ],
      "themes": [
        "Vedic Literature",
        "Purushottama",
        "Krishna",
        "Kshara",
        "Akshara"
      ],
      "content_type": "philosophy",
      "circle_fit": [
        1,
        2
      ],
      "key_quote": "Krishna is actually explaining what does the way all of the Vedic literatures finally boil down to. What is the final statement?",
      "summary": "The speaker introduces verses from the 15th chapter of Bhagavad Gita, where Krishna explains the essence of Vedic literature and the concept of Purushottama, distinguishing between Kshara and Akshara purushas.",
      "timestamp_url": "https://youtu.be/8E1xQmrJR0M?t=1655"
    },
    {
      "start_time": 1771,
      "end_time": 1877,
      "verse_references": [
        "BG 15.18"
      ],
      "themes": [
        "Purushottama",
        "Paramatma",
        "Transcendence",
        "Vedic Literature"
      ],
      "content_type": "philosophy",
      "circle_fit": [
        1,
        2
      ],
      "key_quote": "There is one more third purusha who is anya, different from these kshara and akshara purushas and he is uttama purusha.",
      "summary": "The speaker continues explaining the Bhagavad Gita verses, highlighting the existence of a third Purusha, Uttama Purusha (Purushottama), who is transcendental to both Kshara and Akshara, and is celebrated as Paramatma.",
      "timestamp_url": "https://youtu.be/8E1xQmrJR0M?t=1771"
    },
    {
      "start_time": 1877,
      "end_time": 1977,
      "verse_references": [
        "BG 15.19"
      ],
      "themes": [
        "Krishna",
        "Purushottama",
        "Devotional Service",
        "Understanding"
      ],
      "content_type": "philosophy",
      "circle_fit": [
        1,
        2
      ],
      "key_quote": "One who knows Krishna as that supreme personality doubtlessly...He renders devotional service unto me.",
      "summary": "The speaker emphasizes that one who doubtlessly knows Krishna as the Purushottama renders devotional service to Him with all their heart and devotion.",
      "timestamp_url": "https://youtu.be/8E1xQmrJR0M?t=1877"
    },
    {
      "start_time": 1977,
      "end_time": 2059,
      "verse_references": [],
      "themes": [
        "Krishna",
        "Purushottama",
        "Understanding",
        "Prison Analogy"
      ],
      "content_type": "analogy",
      "circle_fit": [
        2,
        3
      ],
      "key_quote": "One who has understood that, yes, why I have landed in the prison, and I must get out of the prison, by becoming a law-abiding citizen, he has understood the right thing.",
      "summary": "The speaker uses the analogy of a prison to illustrate that true understanding lies in recognizing why we are in the material world and striving to reform ourselves to attain liberation.",
      "timestamp_url": "https://youtu.be/8E1xQmrJR0M?t=1977"
    },
    {
      "start_time": 2061,
      "end_time": 2142,
      "verse_references": [],
      "themes": [
        "Material World",
        "Reformation",
        "Supreme",
        "Duty"
      ],
      "content_type": "philosophy",
      "circle_fit": [
        2,
        3
      ],
      "key_quote": "The material world is there, it's an opportunity for reformation, to understand our relation with the supreme.",
      "summary": "The speaker explains that the material world is an opportunity for reformation and understanding our relationship with the Supreme, contrasting it with merely acquiring worldly knowledge.",
      "timestamp_url": "https://youtu.be/8E1xQmrJR0M?t=2061"
    },
    {
      "start_time": 2142,
      "end_time": 2192,
      "verse_references": [
        "BG 15.20"
      ],
      "themes": [
        "Krishna",
        "Purushottama",
        "Confidential Knowledge",
        "Vedic Literature"
      ],
      "content_type": "philosophy",
      "circle_fit": [
        1,
        2
      ],
      "key_quote": "This understanding Arjuna, is the confidential part, of all Vedic literature.",
      "summary": "The speaker emphasizes that understanding Krishna as the Purushottama and rendering service to Him is the most confidential part of all Vedic literature.",
      "timestamp_url": "https://youtu.be/8E1xQmrJR0M?t=2142"
    },
    {
      "start_time": 2193,
      "end_time": 2305,
      "verse_references": [],
      "themes": [
        "Confidentiality",
        "Paduka Festival",
        "Chaitanya Mahaprabhu",
        "Internal People"
      ],
      "content_type": "story",
      "circle_fit": [
        1,
        2
      ],
      "key_quote": "To everybody, we will show the Paduka, but, real Paduka inside, only a few, you are few people, this is called confidential.",
      "summary": "The speaker shares an anecdote about the upcoming Paduka festival, illustrating the concept of confidentiality by mentioning that the actual wooden Padukas of Chaitanya Mahaprabhu will only be shown to a select few.",
      "timestamp_url": "https://youtu.be/8E1xQmrJR0M?t=2193"
    },
    {
      "start_time": 2305,
      "end_time": 2494,
      "verse_references": [
        "BG 15.20"
      ],
      "themes": [
        "Confidential Knowledge",
        "Krishna",
        "Intelligence",
        "Perfection"
      ],
      "content_type": "philosophy",
      "circle_fit": [
        1,
        2
      ],
      "key_quote": "If you understand this, in this way...you will become an intelligent person...he has attained perfection.",
      "summary": "The speaker reiterates that understanding Krishna as the Purushottama is confidential knowledge, and that understanding this makes one intelligent and leads to perfection, contrasting it with superficial knowledge.",
      "timestamp_url": "https://youtu.be/8E1xQmrJR0M?t=2305"
    },
    {
      "start_time": 2494,
      "end_time": 2588,
      "verse_references": [
        "BG 15.19"
      ],
      "themes": [
        "Krishna",
        "Purushottama",
        "Surrender",
        "Krishna Consciousness"
      ],
      "content_type": "philosophy",
      "circle_fit": [
        1,
        2
      ],
      "key_quote": "Confidently knowing, Krishna is the supreme person, I must surrender to him, and that is perfection.",
      "summary": "The speaker concludes by emphasizing that confidently knowing Krishna as the Supreme Person and surrendering to Him is perfection, lamenting that many commentators miss this point, and highlighting the importance of Krishna consciousness.",
      "timestamp_url": "https://youtu.be/8E1xQmrJR0M?t=2494"
    }
  ]
}