{
  "video_id": "As0zMfjdw4s",
  "title": "Supreme Lord's Assured Protection for Surrendered Souls | Sri Vasudev Keshav Dasa",
  "speaker": "HG Vasudev Keshav Dasa",
  "youtube_url": "https://www.youtube.com/watch?v=As0zMfjdw4s",
  "segments": [
    {
      "start_time": 0,
      "end_time": 46,
      "verse_references": [],
      "themes": [
        "surrender",
        "protection",
        "divine intervention"
      ],
      "content_type": "story",
      "circle_fit": [
        1,
        2,
        3
      ],
      "key_quote": "The Pandavas' life is a wonderful life of surrender and dependence on the Lord.",
      "summary": "The speaker illustrates the Lord's protection of surrendered souls through examples from the Pandavas' lives, highlighting Krishna's interventions in various dangerous situations.",
      "timestamp_url": "https://youtu.be/As0zMfjdw4s?t=0"
    },
    {
      "start_time": 46,
      "end_time": 88,
      "verse_references": [],
      "themes": [
        "faith",
        "chanting",
        "divine plan",
        "protection"
      ],
      "content_type": "philosophy",
      "circle_fit": [
        1,
        2,
        3
      ],
      "key_quote": "So, we must take this name very seriously, very sincerely, chant very attentively and then Krishna's protection is guaranteed.",
      "summary": "The speaker emphasizes the importance of faith in Krishna's protection, even in the face of difficulties, and highlights the power of chanting the Lord's name as a means to secure that protection.",
      "timestamp_url": "https://youtu.be/As0zMfjdw4s?t=46"
    }
  ]
}