{
  "video_id": "cDXJGgPfPWY",
  "title": "Daily Evening Bhagavatam Discourse | HH Stoka Krishna Swami | SB 1.12.20 Part 2 | 22-08-2022",
  "speaker": "HH Stoka Krishna Swami",
  "youtube_url": "https://www.youtube.com/watch?v=cDXJGgPfPWY",
  "segments": [
    {
      "start_time": 49,
      "end_time": 126,
      "verse_references": [
        "SB 1.12.20"
      ],
      "themes": [
        "Srimad Bhagavatam",
        "Verse Analysis",
        "Charity",
        "Protection"
      ],
      "content_type": "philosophy",
      "circle_fit": [
        1,
        2
      ],
      "key_quote": "In this session we will discuss the second part of the purport of this twentieth verse.",
      "summary": "The speaker introduces the session, focusing on the second part of the purport of Srimad Bhagavatam 1.12.20, which discusses charity and protection.",
      "timestamp_url": "https://youtu.be/cDXJGgPfPWY?t=49"
    },
    {
      "start_time": 126,
      "end_time": 283,
      "verse_references": [],
      "themes": [
        "Bharata",
        "Maharaj Dushyanta",
        "Vedic History"
      ],
      "content_type": "story",
      "circle_fit": [
        1,
        2
      ],
      "key_quote": "There are many Bharatas in history of which three are very famous.",
      "summary": "The lecture delves into the history of three famous Bharatas, including the son of Maharaj Dushyanta, the brother of Lord Ramachandra, and the son of King Rishabha.",
      "timestamp_url": "https://youtu.be/cDXJGgPfPWY?t=126"
    },
    {
      "start_time": 283,
      "end_time": 355,
      "verse_references": [],
      "themes": [
        "Vedic Scriptures",
        "Universal History",
        "Knowledge"
      ],
      "content_type": "philosophy",
      "circle_fit": [
        1,
        4
      ],
      "key_quote": "The Vedic scriptures give us knowledge which is comprehensive and vast as compared to the body of knowledge that we have in our modern day.",
      "summary": "The speaker contrasts the comprehensive knowledge of Vedic scriptures with the limited scope of modern-day knowledge, emphasizing the vastness of universal history described in the Vedas.",
      "timestamp_url": "https://youtu.be/cDXJGgPfPWY?t=283"
    },
    {
      "start_time": 355,
      "end_time": 458,
      "verse_references": [],
      "themes": [
        "Bharata Varsha",
        "King Bharata",
        "History"
      ],
      "content_type": "story",
      "circle_fit": [
        1,
        2
      ],
      "key_quote": "This earth planet is known as Bharata, Bharata Varsha due to King Bharata, the son of Rishabhadeva, the second Bharata I mentioned.",
      "summary": "The lecture explains how the earth planet came to be known as Bharata Varsha due to King Bharata, the son of Rishabhadeva, while also highlighting the importance of Bharata, the son of Maharaj Dushyanta.",
      "timestamp_url": "https://youtu.be/cDXJGgPfPWY?t=355"
    },
    {
      "start_time": 458,
      "end_time": 591,
      "verse_references": [],
      "themes": [
        "Shakuntala",
        "Maharaj Dushyanta",
        "Bharata's Childhood",
        "Strength"
      ],
      "content_type": "story",
      "circle_fit": [
        1,
        2
      ],
      "key_quote": "This child Bharata even in his childhood he was so powerful that he challenged the lions and elephants in the forest and would fight with them as little children play with cats and dogs.",
      "summary": "The speaker narrates the story of Bharata's birth to Shakuntala and Maharaj Dushyanta, and his extraordinary strength as a child growing up in the forest, even comparing him to Tarzan.",
      "timestamp_url": "https://youtu.be/cDXJGgPfPWY?t=458"
    },
    {
      "start_time": 591,
      "end_time": 674,
      "verse_references": [],
      "themes": [
        "Sarva Dhaman",
        "Mahabharata",
        "Bharata Dynasty"
      ],
      "content_type": "story",
      "circle_fit": [
        1,
        2
      ],
      "key_quote": "This boy Bharata is not a fictitious character created by some imaginative story writer. No he is a real person and as a boy he was even more powerful than the so-called Tarzan.",
      "summary": "The lecture emphasizes the reality of Bharata's character and his strength, explaining why he was called Sarva Dhaman and how the Pandavas are addressed as Bharata due to their lineage.",
      "timestamp_url": "https://youtu.be/cDXJGgPfPWY?t=591"
    },
    {
      "start_time": 674,
      "end_time": 746,
      "verse_references": [
        "BG 3.14"
      ],
      "themes": [
        "Yajna",
        "Sacrifices",
        "Welfare",
        "Cycle of Nature"
      ],
      "content_type": "philosophy",
      "circle_fit": [
        1,
        2
      ],
      "key_quote": "There is a cycle that is operating in this earth planet.",
      "summary": "The speaker explains the importance of performing sacrifices (yaj単a) for the welfare of the kingdom, highlighting the natural cycle of food production, rainfall, and the role of yaj単a in maintaining this balance.",
      "timestamp_url": "https://youtu.be/cDXJGgPfPWY?t=674"
    },
    {
      "start_time": 746,
      "end_time": 881,
      "verse_references": [
        "BG 3.14"
      ],
      "themes": [
        "Food Production",
        "Rainfall",
        "Yajna",
        "Prescribed Duties"
      ],
      "content_type": "philosophy",
      "circle_fit": [
        1,
        4
      ],
      "key_quote": "So production of grains, sufficient quantity of grains for all creatures, humans and the animals and the other birds etc. depends on proper rainfall.",
      "summary": "The lecture elaborates on the dependence of food production on rainfall, which in turn is dependent on the performance of yaj単a, emphasizing the importance of prescribed duties for the welfare of all beings.",
      "timestamp_url": "https://youtu.be/cDXJGgPfPWY?t=746"
    },
    {
      "start_time": 881,
      "end_time": 967,
      "verse_references": [],
      "themes": [
        "Duties",
        "Yajna",
        "Prosperity",
        "King's Role"
      ],
      "content_type": "philosophy",
      "circle_fit": [
        1,
        2
      ],
      "key_quote": "Duty is something that is prescribed in this jastra for the overall welfare of the entire population of this world.",
      "summary": "The speaker stresses that duties are prescribed for the welfare of all, and the king's role in performing yaj単a leads to prosperity for the entire country, foretelling Pariksit's future role.",
      "timestamp_url": "https://youtu.be/cDXJGgPfPWY?t=881"
    }
  ]
}