{
  "video_id": "gCUZ9dvh6rw",
  "title": "Daily Evening Bhagavatam Discourse | HH Stoka Krishna Swami | SB 1.15.40 | 26-12-2022",
  "speaker": "HH Stoka Krishna Swami",
  "youtube_url": "https://www.youtube.com/watch?v=gCUZ9dvh6rw",
  "segments": [
    {
      "start_time": 0,
      "end_time": 46,
      "verse_references": [],
      "themes": [
        "invocation",
        "prayer"
      ],
      "content_type": "philosophy",
      "circle_fit": [
        1,
        2,
        3,
        4
      ],
      "key_quote": "Om Namo Bhagavate Vasudevaya Narayanam Namaskritya",
      "summary": "The lecture begins with traditional Vaishnava prayers and mantras.",
      "timestamp_url": "https://youtu.be/gCUZ9dvh6rw?t=0"
    },
    {
      "start_time": 46,
      "end_time": 101,
      "verse_references": [
        "SB 1.15.40"
      ],
      "themes": [
        "detachment",
        "renunciation",
        "household life"
      ],
      "content_type": "philosophy",
      "circle_fit": [
        1,
        2
      ],
      "key_quote": "Maharaj Yudhishtira at once relinquished all his garments, belt and ornaments of the royal order and became completely disinterested and unattached to everything",
      "summary": "The speaker introduces the verse from Srimad Bhagavatam describing Maharaj Yudhishtira's detachment from household affairs.",
      "timestamp_url": "https://youtu.be/gCUZ9dvh6rw?t=46"
    },
    {
      "start_time": 101,
      "end_time": 230,
      "verse_references": [],
      "themes": [
        "purification",
        "material contamination",
        "going back to Godhead"
      ],
      "content_type": "philosophy",
      "circle_fit": [
        1,
        2
      ],
      "key_quote": "To become purified of material contamination is the necessary qualification becoming one of the associates of the Lord",
      "summary": "Srila Prabhupada's purport is discussed, emphasizing the need for purification from material contamination to return to Godhead.",
      "timestamp_url": "https://youtu.be/gCUZ9dvh6rw?t=101"
    },
    {
      "start_time": 230,
      "end_time": 373,
      "verse_references": [],
      "themes": [
        "renunciation",
        "vanashrama dharma",
        "simple living"
      ],
      "content_type": "philosophy",
      "circle_fit": [
        1,
        2
      ],
      "key_quote": "Maharaj Yudhishthirath therefore to become spiritually pure spiritually pure means free from all material contamination",
      "summary": "The speaker elaborates on renunciation, referencing the saffron loincloth of a sannyasi and Maharaj Yudhishtira's giving up of royal garments.",
      "timestamp_url": "https://youtu.be/gCUZ9dvh6rw?t=230"
    },
    {
      "start_time": 373,
      "end_time": 487,
      "verse_references": [],
      "themes": [
        "detachment",
        "material designations",
        "bhakti"
      ],
      "content_type": "philosophy",
      "circle_fit": [
        1,
        2
      ],
      "key_quote": "Bhakti means sarva upadhi vinir muktam upadhi means designation to become free from all designations is the way to actually practice bhakti",
      "summary": "The discussion shifts to becoming free from material designations as a key aspect of practicing bhakti.",
      "timestamp_url": "https://youtu.be/gCUZ9dvh6rw?t=373"
    },
    {
      "start_time": 487,
      "end_time": 640,
      "verse_references": [],
      "themes": [
        "designations",
        "attachment",
        "material impurity"
      ],
      "content_type": "philosophy",
      "circle_fit": [
        1,
        2
      ],
      "key_quote": "All these are designations which are the cause for our attachment and bondage in this material world",
      "summary": "Various types of material designations, such as family, society, wealth, and titles, are identified as causes of attachment and bondage.",
      "timestamp_url": "https://youtu.be/gCUZ9dvh6rw?t=487"
    },
    {
      "start_time": 640,
      "end_time": 793,
      "verse_references": [],
      "themes": [
        "renunciation",
        "Chaitanya Mahaprabhu",
        "servant of Krishna"
      ],
      "content_type": "philosophy",
      "circle_fit": [
        1,
        2
      ],
      "key_quote": "Naham vipro na cha narapati na pi vaisho na shudro naham varni na cha grahapati no vanastho yatirva",
      "summary": "The speaker quotes Chaitanya Mahaprabhu's teachings on renouncing even the designations within the heart and identifying oneself as a servant of Krishna.",
      "timestamp_url": "https://youtu.be/gCUZ9dvh6rw?t=640"
    },
    {
      "start_time": 793,
      "end_time": 996,
      "verse_references": [],
      "themes": [
        "devotee",
        "eternal position",
        "sannyasa",
        "humility"
      ],
      "content_type": "philosophy",
      "circle_fit": [
        1,
        2,
        3
      ],
      "key_quote": "Everyone, every living being, we are eternally Krishna's servants or Krishna's devotees.",
      "summary": "The lecture concludes by emphasizing that being a devotee of Krishna is our eternal position, and the role of a sannyasi is to disseminate spiritual knowledge without expecting anything in return, maintaining humility.",
      "timestamp_url": "https://youtu.be/gCUZ9dvh6rw?t=793"
    }
  ]
}