{
  "video_id": "gjUWKTLaLSU",
  "title": "Who Truly Owns Everything? | Sri Chanchalapathi Dasa @ChanchalapathiDas",
  "speaker": "HG Chanchalapathi Dasa",
  "youtube_url": "https://www.youtube.com/watch?v=gjUWKTLaLSU",
  "segments": [
    {
      "start_time": 0,
      "end_time": 60,
      "verse_references": [],
      "themes": [
        "ownership",
        "belonging",
        "devotion"
      ],
      "content_type": "philosophy",
      "circle_fit": [
        1,
        2,
        3
      ],
      "key_quote": "We must use all of this to serve Rama",
      "summary": "The speaker establishes that everything, including our bodies and strength, belongs to Sri Rama, and we should use them in His service.",
      "timestamp_url": "https://youtu.be/gjUWKTLaLSU?t=0"
    }
  ]
}