{
  "video_id": "jR_9igBGf2Y",
  "title": "Daily Evening Bhagavatam Discourse | HH Stoka Krishna Swami | SB 1.9.40 | 09-05-2022",
  "speaker": "HH Stoka Krishna Swami",
  "youtube_url": "https://www.youtube.com/watch?v=jR_9igBGf2Y",
  "segments": [
    {
      "start_time": 37,
      "end_time": 481,
      "verse_references": [
        "SB 1.9.40"
      ],
      "themes": [
        "bhakti",
        "Gopis' devotion",
        "pure devotion",
        "conjugal love"
      ],
      "content_type": "philosophy",
      "circle_fit": [
        1,
        2
      ],
      "key_quote": "They simply want to please Krishna. That's all.",
      "summary": "This segment explains Bhishma Deva's prayer to Krishna, focusing on the Gopis' unparalleled pure devotion characterized by selfless love and a desire only to please Krishna, contrasting it with other forms of worship motivated by personal gain or knowledge.",
      "timestamp_url": "https://youtu.be/jR_9igBGf2Y?t=37"
    },
    {
      "start_time": 481,
      "end_time": 677,
      "verse_references": [],
      "themes": [
        "types of devotees",
        "pure vs. mixed devotion",
        "Gopis' supreme devotion"
      ],
      "content_type": "philosophy",
      "circle_fit": [
        1,
        2
      ],
      "key_quote": "Whereas, the pure devotees do not want anything in return for their worship or in return for their service to Krishna.",
      "summary": "This segment differentiates between devotees who approach Krishna with ulterior motives (Artha, Artharthi, Jignasu, Jnani) and pure devotees like the Gopis, who seek nothing in return for their selfless service, highlighting the Gopis' supreme position in devotional service.",
      "timestamp_url": "https://youtu.be/jR_9igBGf2Y?t=481"
    },
    {
      "start_time": 677,
      "end_time": 906,
      "verse_references": [],
      "themes": [
        "Gopis' mercy",
        "equality with the Lord",
        "unconditional love",
        "selfish vs. selfless interest"
      ],
      "content_type": "philosophy",
      "circle_fit": [
        1,
        2
      ],
      "key_quote": "The Lord, Supreme Lord Krishna, is always more satisfied when his pure devotees are glorified.",
      "summary": "This segment discusses Bhishma's aspiration for the Gopis' mercy, their equality with the Lord through perfect ecstasy, and the nature of unconditional love between Krishna and the Gopis, contrasting it with the selfish desire of Mayavadis to merge into God's existence.",
      "timestamp_url": "https://youtu.be/jR_9igBGf2Y?t=677"
    }
  ]
}