{
  "video_id": "ORIHp5uJvWI",
  "title": "Daily Evening Bhagavatam Discourse | HH Stoka Krishna Swami | SB 1.9.6-7 | 30-03-2022",
  "speaker": "HH Stoka Krishna Swami",
  "youtube_url": "https://www.youtube.com/watch?v=ORIHp5uJvWI",
  "segments": [
    {
      "start_time": 0,
      "end_time": 42,
      "verse_references": [],
      "themes": [
        "invocation",
        "mantras",
        "guru"
      ],
      "content_type": "philosophy",
      "circle_fit": [
        1,
        2,
        3,
        4
      ],
      "key_quote": "Om Agyana Timiran Dhasya Gyanan Janishalakaya Chakshuran Militam Yena Tasmai Shri Gurave Namaha",
      "summary": "The lecture begins with traditional Vaishnava prayers and mantras, invoking blessings and paying respects to the spiritual master.",
      "timestamp_url": "https://youtu.be/ORIHp5uJvWI?t=0"
    },
    {
      "start_time": 42,
      "end_time": 114,
      "verse_references": [
        "SB 1.9.6",
        "SB 1.9.7"
      ],
      "themes": [
        "sages",
        "presence",
        "assembly"
      ],
      "content_type": "story",
      "circle_fit": [
        1,
        2
      ],
      "key_quote": "The meaning of these two verses, all the sages like Parvatamuni, Narada, Dhaumya, Vyasa, the Incarnation of God, Brihadashva, Bharadvaja, and Parshurama and disciples, Vasishta, Indra Pramada, Trita, Gritsamada, Asita, Kakshivan, Gautama, Atri, Kaushika, and Sudarshana were present.",
      "summary": "The speaker introduces the verses to be discussed and lists the names of the sages present at the assembly.",
      "timestamp_url": "https://youtu.be/ORIHp5uJvWI?t=42"
    },
    {
      "start_time": 114,
      "end_time": 221,
      "verse_references": [],
      "themes": [
        "Narada Muni",
        "disciplic succession",
        "parampara"
      ],
      "content_type": "philosophy",
      "circle_fit": [
        1,
        2
      ],
      "key_quote": "Narada Muni is inevitably associated with the narrations of the Puranas.",
      "summary": "The speaker begins to explain the biographies of some of the sages mentioned in the verses, starting with Narada Muni and his role in the disciplic succession.",
      "timestamp_url": "https://youtu.be/ORIHp5uJvWI?t=114"
    },
    {
      "start_time": 221,
      "end_time": 334,
      "verse_references": [],
      "themes": [
        "preaching",
        "devotees",
        "disciplic succession",
        "Narada Muni"
      ],
      "content_type": "philosophy",
      "circle_fit": [
        1,
        2
      ],
      "key_quote": "So, Srila Prabhupada explains that this parampara understanding is required in all places in the material creation.",
      "summary": "The speaker continues discussing the importance of disciplic succession and the role of pure devotees in spreading knowledge, highlighting Narada Muni's instructions to various kings and devotees.",
      "timestamp_url": "https://youtu.be/ORIHp5uJvWI?t=221"
    },
    {
      "start_time": 334,
      "end_time": 433,
      "verse_references": [],
      "themes": [
        "Dhaumya Rishi",
        "Pandavas",
        "guidance",
        "exile"
      ],
      "content_type": "story",
      "circle_fit": [
        1,
        2
      ],
      "key_quote": "A great sage who practiced severe penances at Utkochaka Tirtha and was appointed royal priest to the Pandava kings.",
      "summary": "The speaker shifts focus to Dhaumya Rishi, describing his role as the royal priest and advisor to the Pandavas, particularly during their exile.",
      "timestamp_url": "https://youtu.be/ORIHp5uJvWI?t=334"
    },
    {
      "start_time": 433,
      "end_time": 558,
      "verse_references": [],
      "themes": [
        "Pandavas",
        "Dhaumya Rishi",
        "incognito",
        "instructions"
      ],
      "content_type": "story",
      "circle_fit": [
        1,
        2
      ],
      "key_quote": "Dhaumya Rishi gave Pandavas instructions how to live one year incognito and they were successful in living so.",
      "summary": "The speaker elaborates on Dhaumya Rishi's guidance to the Pandavas during their incognito exile and his presence at the funeral ceremony after the Kurukshetra war.",
      "timestamp_url": "https://youtu.be/ORIHp5uJvWI?t=433"
    },
    {
      "start_time": 558,
      "end_time": 656,
      "verse_references": [],
      "themes": [
        "guidance",
        "householders",
        "priests",
        "ashrama dharma"
      ],
      "content_type": "philosophy",
      "circle_fit": [
        1,
        2
      ],
      "key_quote": "You see guidance is required from a transcendentalist.",
      "summary": "The speaker explains the importance of guidance from transcendentalists for householders and the role of priests in guiding individuals according to their ashrama dharma.",
      "timestamp_url": "https://youtu.be/ORIHp5uJvWI?t=558"
    },
    {
      "start_time": 656,
      "end_time": 784,
      "verse_references": [],
      "themes": [
        "Vyasadeva",
        "incarnation",
        "Vedic wisdom",
        "Bhagavatam"
      ],
      "content_type": "philosophy",
      "circle_fit": [
        1,
        2
      ],
      "key_quote": "Vyasadeva or Vedavyasa is a powerful incarnation of Narayana. And he broadcasts the Vedic wisdom to the world.",
      "summary": "The speaker begins to describe Vyasadeva, his various names, his role as an incarnation of Narayana, and his contribution to compiling and transmitting Vedic knowledge, including the Bhagavatam.",
      "timestamp_url": "https://youtu.be/ORIHp5uJvWI?t=656"
    },
    {
      "start_time": 784,
      "end_time": 933,
      "verse_references": [],
      "themes": [
        "Vyasadeva",
        "penances",
        "Mahabharata",
        "Ganesha",
        "sons"
      ],
      "content_type": "story",
      "circle_fit": [
        1,
        2
      ],
      "key_quote": "When Vyasadeva wanted to record the great epic Mahabharata for the welfare of all people in the age of Kali, he was feeling the necessity of a powerful writer who could take up his dictation.",
      "summary": "The speaker continues describing Vyasadeva's life, including his penances, the compilation of the Mahabharata with the help of Ganesha, and the birth of his three sons.",
      "timestamp_url": "https://youtu.be/ORIHp5uJvWI?t=784"
    }
  ]
}