{
  "video_id": "z9-Or6fYEdA",
  "title": "SB 1.18.48 | HH Stoka Krishna Swami | 30-04-2023 | Daily Evening Bhagavatam Discourse",
  "speaker": "HH Stoka Krishna Swami",
  "youtube_url": "https://www.youtube.com/watch?v=z9-Or6fYEdA",
  "segments": [
    {
      "start_time": 0,
      "end_time": 47,
      "verse_references": [],
      "themes": [
        "invocation",
        "prayer"
      ],
      "content_type": "philosophy",
      "circle_fit": [
        1,
        2,
        3
      ],
      "key_quote": "Om Namo Bhagavate Vasudevaya Narayanam Namaskritya",
      "summary": "The lecture begins with traditional Vaishnava prayers and mantras.",
      "timestamp_url": "https://youtu.be/z9-Or6fYEdA?t=0"
    },
    {
      "start_time": 48,
      "end_time": 137,
      "verse_references": [
        "SB 3.25.21"
      ],
      "themes": [
        "tolerance",
        "devotion",
        "forbearance"
      ],
      "content_type": "philosophy",
      "circle_fit": [
        1,
        2
      ],
      "key_quote": "The devotees of the Lord are so forbearing that even though they are defamed, cheated, cursed, disturbed, neglected or even killed they are never inclined to avenge themselves",
      "summary": "The speaker introduces the verse and explains that pure devotees are tolerant and do not retaliate even when wronged.",
      "timestamp_url": "https://youtu.be/z9-Or6fYEdA?t=48"
    },
    {
      "start_time": 138,
      "end_time": 307,
      "verse_references": [],
      "themes": [
        "devotee protection",
        "divine justice",
        "offenses"
      ],
      "content_type": "story",
      "circle_fit": [
        1,
        2
      ],
      "key_quote": "The supreme lord cannot tolerate his devotee being harmed by anybody else",
      "summary": "The speaker narrates the story of Durvasa Muni and Ambarisha Maharaja to illustrate how the Lord protects his devotees and punishes those who offend them.",
      "timestamp_url": "https://youtu.be/z9-Or6fYEdA?t=138"
    },
    {
      "start_time": 308,
      "end_time": 406,
      "verse_references": [],
      "themes": [
        "forgiveness",
        "devotee power",
        "humility"
      ],
      "content_type": "philosophy",
      "circle_fit": [
        1,
        2
      ],
      "key_quote": "A pure devotee is callous about worldly advantages or reverses.",
      "summary": "The speaker continues to explain the qualities of a pure devotee, emphasizing their indifference to worldly gains and losses and their willingness to tolerate personal offenses.",
      "timestamp_url": "https://youtu.be/z9-Or6fYEdA?t=308"
    },
    {
      "start_time": 407,
      "end_time": 575,
      "verse_references": [],
      "themes": [
        "humility",
        "self-perception",
        "divine mercy"
      ],
      "content_type": "philosophy",
      "circle_fit": [
        1,
        2
      ],
      "key_quote": "He considers that to be the mercy of the Supreme Personality of Godhead",
      "summary": "The speaker quotes a verse spoken by Brahma, explaining that pure devotees see difficulties as the mercy of the Lord and believe they deserve worse punishment for their past misdeeds.",
      "timestamp_url": "https://youtu.be/z9-Or6fYEdA?t=407"
    },
    {
      "start_time": 576,
      "end_time": 695,
      "verse_references": [],
      "themes": [
        "justice",
        "devotee responsibility",
        "offenses"
      ],
      "content_type": "philosophy",
      "circle_fit": [
        1,
        2
      ],
      "key_quote": "Then this pure devotee will not tolerate will not sit quiet. He will take proper action against the offender",
      "summary": "The speaker contrasts the devotee's tolerance of personal offenses with their active response to offenses against the Lord or other devotees, explaining why Shamika Rishi appealed to the Lord instead of Pariksit Maharaja.",
      "timestamp_url": "https://youtu.be/z9-Or6fYEdA?t=576"
    },
    {
      "start_time": 696,
      "end_time": 898,
      "verse_references": [],
      "themes": [
        "devotee power",
        "service",
        "example"
      ],
      "content_type": "philosophy",
      "circle_fit": [
        1,
        2
      ],
      "key_quote": "A pure devotee is the most powerful personality in the entire creation.",
      "summary": "The speaker emphasizes the power of a pure devotee, even exceeding that of a brahmana, and illustrates this with the example of Hanuman burning Lanka after Ravana insulted Lord Rama, highlighting that this power is used only in service to the Lord and his devotees.",
      "timestamp_url": "https://youtu.be/z9-Or6fYEdA?t=696"
    },
    {
      "start_time": 898,
      "end_time": 900,
      "verse_references": [],
      "themes": [
        "conclusion"
      ],
      "content_type": "practical",
      "circle_fit": [
        1,
        2,
        3,
        4
      ],
      "key_quote": "Hare Krishna.",
      "summary": "The speaker concludes the lecture with a closing statement and the Hare Krishna mantra.",
      "timestamp_url": "https://youtu.be/z9-Or6fYEdA?t=898"
    }
  ]
}