{
  "video_id": "zlhVbxdrWgQ",
  "title": "Japa is a relationship with Krishna   Soulful Japa",
  "speaker": "HH Stoka Krishna Maharaj",
  "youtube_url": "https://www.youtube.com/watch?v=zlhVbxdrWgQ",
  "segments": [
    {
      "start_time": 0,
      "end_time": 62,
      "verse_references": [],
      "themes": [
        "japa",
        "relationship with Krishna",
        "chanting"
      ],
      "content_type": "philosophy",
      "circle_fit": [
        1,
        2,
        3
      ],
      "key_quote": "But eventually Japa is a relationship with Krishna.",
      "summary": "Japa is presented as a process that evolves into a relationship with Krishna through chanting and hearing the Hare Krishna mantra.",
      "timestamp_url": "https://youtu.be/zlhVbxdrWgQ?t=0"
    }
  ]
}